boto3auth/__init__.py
boto3auth-1.1.0.dist-info/LICENSE
boto3auth-1.1.0.dist-info/METADATA
boto3auth-1.1.0.dist-info/WHEEL
boto3auth-1.1.0.dist-info/top_level.txt
boto3auth-1.1.0.dist-info/RECORD
