Metadata-Version: 2.1
Name: boto3auth
Version: 1.1.0
Summary: Simple wrapper for starting Boto3 clients/resources.
Home-page: https://github.com/mtslzr/boto3auth
Author: Matthew Salazar
Author-email: m@tthewsalazar.com
License: UNKNOWN
Platform: UNKNOWN
Classifier: Programming Language :: Python :: 3
Classifier: License :: OSI Approved :: MIT License
Classifier: Operating System :: OS Independent
Requires-Dist: boto3
